ghflowgen/__init__.py
ghflowgen/utils/__init__.py
ghflowgen/utils/export.py
ghflowgen/utils/pypi.py
ghflowgen/version/__init__.py
ghflowgen/version/comparison.py
ghflowgen/version/filtering.py
ghflowgen/version/package.py
ghflowgen/version/runtime.py
ghflowgen-0.0.1.dist-info/METADATA
ghflowgen-0.0.1.dist-info/WHEEL
ghflowgen-0.0.1.dist-info/licenses/LICENSE
ghflowgen-0.0.1.dist-info/RECORD
